userpath/__init__.py
userpath/__main__.py
userpath/cli.py
userpath/core.py
userpath/interface.py
userpath/shells.py
userpath/utils.py
userpath-1.7.0.dist-info/LICENSE-APACHE
userpath-1.7.0.dist-info/LICENSE-MIT
userpath-1.7.0.dist-info/METADATA
userpath-1.7.0.dist-info/WHEEL
userpath-1.7.0.dist-info/entry_points.txt
userpath-1.7.0.dist-info/top_level.txt
userpath-1.7.0.dist-info/RECORD
