Metadata-Version: 1.2
Name: userpath
Version: 1.7.0
Summary: Cross-platform tool for adding locations to the user PATH, no elevated privileges required!
Home-page: https://github.com/ofek/userpath
Author: Ofek Lev
Author-email: ofekmeister@gmail.com
Maintainer: Ofek Lev
Maintainer-email: ofekmeister@gmail.com
License: MIT OR Apache-2.0
Keywords: scripts,user path,path,cli
Platform: UNKNOWN
Classifier: Development Status :: 4 - Beta
Classifier: Intended Audience :: Developers
Classifier: License :: OSI Approved :: MIT License
Classifier: License :: OSI Approved :: Apache Software License
Classifier: Natural Language :: English
Classifier: Operating System :: OS Independent
Classifier: Programming Language :: Python :: 2.7
Classifier: Programming Language :: Python :: 3.6
Classifier: Programming Language :: Python :: 3.7
Classifier: Programming Language :: Python :: 3.8
Classifier: Programming Language :: Python :: 3.9
Classifier: Programming Language :: Python :: Implementation :: CPython
Classifier: Programming Language :: Python :: Implementation :: PyPy
